omerai/__init__.py
omerai/core.py
omerai-0.0.7.dist-info/METADATA
omerai-0.0.7.dist-info/WHEEL
omerai-0.0.7.dist-info/top_level.txt
omerai-0.0.7.dist-info/RECORD
