Metadata-Version: 2.4
Name: omerai
Version: 0.0.7
Summary: AI image generator — DreamRender
Author: Omer
Author-email: omertech1230@gmail.com
Classifier: Programming Language :: Python :: 3
Classifier: License :: OSI Approved :: MIT License
Classifier: Operating System :: OS Independent
Requires-Python: >=3.7
Requires-Dist: requests
Dynamic: author
Dynamic: author-email
Dynamic: classifier
Dynamic: requires-dist
Dynamic: requires-python
Dynamic: summary
